hack4u/__init__.py
hack4u/cursos.py
hack4u/utils.py
pr_ctica_1_hack4u-0.1.0.dist-info/METADATA
pr_ctica_1_hack4u-0.1.0.dist-info/WHEEL
pr_ctica_1_hack4u-0.1.0.dist-info/top_level.txt
pr_ctica_1_hack4u-0.1.0.dist-info/RECORD
