Metadata-Version: 2.1
Name: pr-ctica-1-hack4u
Version: 0.1.0
Summary: Una práctica de biblioteca donde consultar cursos de hack4u.
Home-page: https://hack4u.io
Author: Aport
